Metadata-Version: 2.1
Name: pixitsvini
Version: 1.0.0
Summary: QRCode Pix for python
Home-page: https://github.com/itzvini/pix-qrcode
Author: Joao Carlos
Author-email: joao-mostela@hotmail.com
Requires-Dist: qrcode
